pipenv2setup/__init__.py
pipenv2setup/__main__.py
pipenv2setup/core.py
pipenv2setup-0.1.3.dist-info/LICENSE
pipenv2setup-0.1.3.dist-info/METADATA
pipenv2setup-0.1.3.dist-info/WHEEL
pipenv2setup-0.1.3.dist-info/top_level.txt
pipenv2setup-0.1.3.dist-info/RECORD
