Metadata-Version: 2.1
Name: pipenv2setup
Version: 0.1.3
Summary: Library to generate install_requires.py file from pipfile
Home-page: https://github.com/alanbacon/pipenv2setup
Author: Alan Bacon
Author-email: alan@bacontowers.co.uk
License: UNKNOWN
Platform: UNKNOWN
Classifier: Programming Language :: Python :: 3
Classifier: License :: OSI Approved :: MIT License
Requires-Dist: tomlkit
